README.md
setup.cfg
setup.py
DecoratorHelper/DecoratorHelper.py
DecoratorHelper/__init__.py
DecoratorHelper.egg-info/PKG-INFO
DecoratorHelper.egg-info/SOURCES.txt
DecoratorHelper.egg-info/dependency_links.txt
DecoratorHelper.egg-info/not-zip-safe
DecoratorHelper.egg-info/top_level.txt