Metadata-Version: 1.0
Name: DecoratorHelper
Version: 1.0
Summary: This class is intended for decorating called objects.
Home-page: UNKNOWN
Author: UNKNOWN
Author-email: ivandusheko@mail.ru
License: UNKNOWN
Platform: UNKNOWN
